my_own_package/__init__.py
herb_package_boi-0.2.0.dist-info/METADATA
herb_package_boi-0.2.0.dist-info/WHEEL
herb_package_boi-0.2.0.dist-info/top_level.txt
herb_package_boi-0.2.0.dist-info/RECORD
