Metadata-Version: 2.1
Name: herb-package-boi
Version: 0.2.0
Summary: my_first_package
Author: Fetz Herbert
Author-email: fetz.martin.herbert.ovb@gmail.com
